[
  {
    "state": "Alabama",
    "year": 2010,
    "volunteerPercent": 24,
    "volunteerRank": 34,
    "volunteerHours": 22.49,
    "volunteerHoursRank": 43,
    "meetingPercent": 9.7,
    "meetingRank": 26,
    "communityPercent": 10,
    "communityRank": 19,
    "donatedPercent": 56.7,
    "donatedRank": 14,
    "votePercent": 44.1,
    "voteRank": 34,
    "registeredPercent": 65,
    "registeredRank": 31,
    "contactedPercent": 8.1,
    "contactedRank": 41,
    "productPercent": 6.5,
    "productRank": 45,
    "groupPercent": 12.5,
    "groupRank": 34,
    "organizationPercent": 7.2,
    "organizationRank": 24
  },
  {
    "state": "Alaska",
    "year": 2010,
    "volunteerPercent": 27.9,
    "volunteerRank": 19,
    "volunteerHours": 34.45,
    "volunteerHoursRank": 7,
    "meetingPercent": 13.9,
    "meetingRank": 10,
    "communityPercent": 13.4,
    "communityRank": 7,
    "donatedPercent": 57.4,
    "donatedRank": 10,
    "votePercent": 50.7,
    "voteRank": 15,
    "registeredPercent": 66.4,
    "registeredRank": 23,
    "contactedPercent": 17.1,
    "contactedRank": 5,
    "productPercent": 14,
    "productRank": 8,
    "groupPercent": 15.9,
    "groupRank": 10,
    "organizationPercent": 12.4,
    "organizationRank": 2
  },
  {
    "state": "Arizona",
    "year": 2010,
    "volunteerPercent": 22.3,
    "volunteerRank": 40,
    "volunteerHours": 28.87,
    "volunteerHoursRank": 21,
    "meetingPercent": 9.5,
    "meetingRank": 29,
    "communityPercent": 8.2,
    "communityRank": 28,
    "donatedPercent": 51.4,
    "donatedRank": 28,
    "votePercent": 48.8,
    "voteRank": 18,
    "registeredPercent": 66,
    "registeredRank": 27,
    "contactedPercent": 9.9,
    "contactedRank": 32,
    "productPercent": 7.5,
    "productRank": 37,
    "groupPercent": 10.4,
    "groupRank": 48,
    "organizationPercent": 5.4,
    "organizationRank": 41
  },
  {
    "state": "Arkansas",
    "year": 2010,
    "volunteerPercent": 20.2,
    "volunteerRank": 48,
    "volunteerHours": 18.3,
    "volunteerHoursRank": 51,
    "meetingPercent": 6.8,
    "meetingRank": 51,
    "communityPercent": 6.2,
    "communityRank": 48,
    "donatedPercent": 50,
    "donatedRank": 36,
    "votePercent": 40.7,
    "voteRank": 45,
    "registeredPercent": 60.7,
    "registeredRank": 47,
    "contactedPercent": 7.8,
    "contactedRank": 44,
    "productPercent": 4.2,
    "productRank": 51,
    "groupPercent": 12.2,
    "groupRank": 38,
    "organizationPercent": 5.3,
    "organizationRank": 42
  },
  {
    "state": "California",
    "year": 2010,
    "volunteerPercent": 22.9,
    "volunteerRank": 37,
    "volunteerHours": 26.24,
    "volunteerHoursRank": 29,
    "meetingPercent": 8.1,
    "meetingRank": 37,
    "communityPercent": 7.4,
    "communityRank": 35,
    "donatedPercent": 47.6,
    "donatedRank": 41,
    "votePercent": 47.1,
    "voteRank": 23,
    "registeredPercent": 60.9,
    "registeredRank": 45,
    "contactedPercent": 8.5,
    "contactedRank": 39,
    "productPercent": 10.8,
    "productRank": 20,
    "groupPercent": 12.9,
    "groupRank": 32,
    "organizationPercent": 4.3,
    "organizationRank": 49
  },
  {
    "state": "Colorado",
    "year": 2010,
    "volunteerPercent": 30.9,
    "volunteerRank": 11,
    "volunteerHours": 32.84,
    "volunteerHoursRank": 9,
    "meetingPercent": 11.6,
    "meetingRank": 17,
    "communityPercent": 8.8,
    "communityRank": 26,
    "donatedPercent": 58.1,
    "donatedRank": 6,
    "votePercent": 52.6,
    "voteRank": 9,
    "registeredPercent": 66.2,
    "registeredRank": 25,
    "contactedPercent": 12.4,
    "contactedRank": 22,
    "productPercent": 16.6,
    "productRank": 5,
    "groupPercent": 18.1,
    "groupRank": 1,
    "organizationPercent": 9.2,
    "organizationRank": 15
  },
  {
    "state": "Connecticut",
    "year": 2010,
    "volunteerPercent": 29.7,
    "volunteerRank": 15,
    "volunteerHours": 24.62,
    "volunteerHoursRank": 33,
    "meetingPercent": 10.9,
    "meetingRank": 19,
    "communityPercent": 7.4,
    "communityRank": 35,
    "donatedPercent": 58.7,
    "donatedRank": 5,
    "votePercent": 49.3,
    "voteRank": 17,
    "registeredPercent": 66.6,
    "registeredRank": 21,
    "contactedPercent": 13.4,
    "contactedRank": 13,
    "productPercent": 13.6,
    "productRank": 10,
    "groupPercent": 14.2,
    "groupRank": 21,
    "organizationPercent": 8.4,
    "organizationRank": 19
  },
  {
    "state": "DC",
    "year": 2010,
    "volunteerPercent": 26.3,
    "volunteerRank": 27,
    "volunteerHours": 28.12,
    "volunteerHoursRank": 23,
    "meetingPercent": 14.2,
    "meetingRank": 8,
    "communityPercent": 13.4,
    "communityRank": 7,
    "donatedPercent": 48.1,
    "donatedRank": 40,
    "votePercent": 45.3,
    "voteRank": 32,
    "registeredPercent": 66.9,
    "registeredRank": 19,
    "contactedPercent": 17.7,
    "contactedRank": 3,
    "productPercent": 16.3,
    "productRank": 6,
    "groupPercent": 16.6,
    "groupRank": 8,
    "organizationPercent": 6.9,
    "organizationRank": 30
  },
  {
    "state": "Delaware",
    "year": 2010,
    "volunteerPercent": 20,
    "volunteerRank": 49,
    "volunteerHours": 18.89,
    "volunteerHoursRank": 48,
    "meetingPercent": 7.4,
    "meetingRank": 43,
    "communityPercent": 6.1,
    "communityRank": 50,
    "donatedPercent": 50.3,
    "donatedRank": 33,
    "votePercent": 51,
    "voteRank": 13,
    "registeredPercent": 65.9,
    "registeredRank": 29,
    "contactedPercent": 10.2,
    "contactedRank": 31,
    "productPercent": 7.2,
    "productRank": 39,
    "groupPercent": 15.7,
    "groupRank": 13,
    "organizationPercent": 7.2,
    "organizationRank": 24
  },
  {
    "state": "Florida",
    "year": 2010,
    "volunteerPercent": 19.3,
    "volunteerRank": 50,
    "volunteerHours": 23.31,
    "volunteerHoursRank": 40,
    "meetingPercent": 7.1,
    "meetingRank": 46,
    "communityPercent": 6.8,
    "communityRank": 43,
    "donatedPercent": 42.1,
    "donatedRank": 51,
    "votePercent": 43.9,
    "voteRank": 35,
    "registeredPercent": 63,
    "registeredRank": 38,
    "contactedPercent": 7.7,
    "contactedRank": 45,
    "productPercent": 8.5,
    "productRank": 34,
    "groupPercent": 10.7,
    "groupRank": 47,
    "organizationPercent": 6.3,
    "organizationRank": 34
  },
  {
    "state": "Georgia",
    "year": 2010,
    "volunteerPercent": 20.9,
    "volunteerRank": 44,
    "volunteerHours": 23.29,
    "volunteerHoursRank": 41,
    "meetingPercent": 6.9,
    "meetingRank": 49,
    "communityPercent": 6.7,
    "communityRank": 44,
    "donatedPercent": 46.5,
    "donatedRank": 43,
    "votePercent": 43.6,
    "voteRank": 37,
    "registeredPercent": 62,
    "registeredRank": 41,
    "contactedPercent": 8.9,
    "contactedRank": 36,
    "productPercent": 10.9,
    "productRank": 19,
    "groupPercent": 17.8,
    "groupRank": 2,
    "organizationPercent": 5.2,
    "organizationRank": 45
  },
  {
    "state": "Hawaii",
    "year": 2010,
    "volunteerPercent": 20.9,
    "volunteerRank": 44,
    "volunteerHours": 29.79,
    "volunteerHoursRank": 18,
    "meetingPercent": 8.1,
    "meetingRank": 37,
    "communityPercent": 7.3,
    "communityRank": 38,
    "donatedPercent": 48.3,
    "donatedRank": 39,
    "votePercent": 43.1,
    "voteRank": 39,
    "registeredPercent": 52.3,
    "registeredRank": 51,
    "contactedPercent": 7.1,
    "contactedRank": 49,
    "productPercent": 6.1,
    "productRank": 47,
    "groupPercent": 11.9,
    "groupRank": 41,
    "organizationPercent": 4.8,
    "organizationRank": 48
  },
  {
    "state": "Idaho",
    "year": 2010,
    "volunteerPercent": 33.9,
    "volunteerRank": 7,
    "volunteerHours": 42.19,
    "volunteerHoursRank": 2,
    "meetingPercent": 12.2,
    "meetingRank": 14,
    "communityPercent": 14,
    "communityRank": 4,
    "donatedPercent": 57,
    "donatedRank": 12,
    "votePercent": 47.5,
    "voteRank": 19,
    "registeredPercent": 63.5,
    "registeredRank": 37,
    "contactedPercent": 11.1,
    "contactedRank": 25,
    "productPercent": 9.9,
    "productRank": 27,
    "groupPercent": 17.8,
    "groupRank": 2,
    "organizationPercent": 8.7,
    "organizationRank": 17
  },
  {
    "state": "Illinois",
    "year": 2010,
    "volunteerPercent": 26.7,
    "volunteerRank": 22,
    "volunteerHours": 29.71,
    "volunteerHoursRank": 19,
    "meetingPercent": 7.8,
    "meetingRank": 41,
    "communityPercent": 6.9,
    "communityRank": 42,
    "donatedPercent": 52.8,
    "donatedRank": 25,
    "votePercent": 45.5,
    "voteRank": 30,
    "registeredPercent": 66.3,
    "registeredRank": 24,
    "contactedPercent": 10.8,
    "contactedRank": 26,
    "productPercent": 10.8,
    "productRank": 20,
    "groupPercent": 13.3,
    "groupRank": 29,
    "organizationPercent": 6,
    "organizationRank": 39
  },
  {
    "state": "Indiana",
    "year": 2010,
    "volunteerPercent": 24.8,
    "volunteerRank": 30,
    "volunteerHours": 22.85,
    "volunteerHoursRank": 42,
    "meetingPercent": 7.3,
    "meetingRank": 45,
    "communityPercent": 6.5,
    "communityRank": 45,
    "donatedPercent": 45.5,
    "donatedRank": 46,
    "votePercent": 39.4,
    "voteRank": 48,
    "registeredPercent": 61.2,
    "registeredRank": 43,
    "contactedPercent": 10.4,
    "contactedRank": 29,
    "productPercent": 7.8,
    "productRank": 36,
    "groupPercent": 13.9,
    "groupRank": 22,
    "organizationPercent": 9.6,
    "organizationRank": 12
  },
  {
    "state": "Iowa",
    "year": 2010,
    "volunteerPercent": 35.1,
    "volunteerRank": 5,
    "volunteerHours": 26.6,
    "volunteerHoursRank": 28,
    "meetingPercent": 11.9,
    "meetingRank": 15,
    "communityPercent": 10.4,
    "communityRank": 15,
    "donatedPercent": 55,
    "donatedRank": 20,
    "votePercent": 52.3,
    "voteRank": 10,
    "registeredPercent": 70.8,
    "registeredRank": 9,
    "contactedPercent": 13.4,
    "contactedRank": 13,
    "productPercent": 10.3,
    "productRank": 23,
    "groupPercent": 11.7,
    "groupRank": 43,
    "organizationPercent": 11.9,
    "organizationRank": 3
  },
  {
    "state": "Kansas",
    "year": 2010,
    "volunteerPercent": 33.8,
    "volunteerRank": 8,
    "volunteerHours": 29.15,
    "volunteerHoursRank": 20,
    "meetingPercent": 11.1,
    "meetingRank": 18,
    "communityPercent": 10.7,
    "communityRank": 13,
    "donatedPercent": 57.8,
    "donatedRank": 9,
    "votePercent": 47.2,
    "voteRank": 21,
    "registeredPercent": 68.4,
    "registeredRank": 16,
    "contactedPercent": 13.3,
    "contactedRank": 15,
    "productPercent": 10.2,
    "productRank": 25,
    "groupPercent": 15.8,
    "groupRank": 11,
    "organizationPercent": 11.4,
    "organizationRank": 6
  },
  {
    "state": "Kentucky",
    "year": 2010,
    "volunteerPercent": 21.5,
    "volunteerRank": 43,
    "volunteerHours": 18.79,
    "volunteerHoursRank": 49,
    "meetingPercent": 7.1,
    "meetingRank": 46,
    "communityPercent": 6.4,
    "communityRank": 46,
    "donatedPercent": 45.3,
    "donatedRank": 47,
    "votePercent": 46.8,
    "voteRank": 26,
    "registeredPercent": 66.9,
    "registeredRank": 19,
    "contactedPercent": 8.9,
    "contactedRank": 36,
    "productPercent": 6,
    "productRank": 48,
    "groupPercent": 10.1,
    "groupRank": 50,
    "organizationPercent": 5.3,
    "organizationRank": 42
  },
  {
    "state": "Louisiana",
    "year": 2010,
    "volunteerPercent": 22.1,
    "volunteerRank": 41,
    "volunteerHours": 26.78,
    "volunteerHoursRank": 27,
    "meetingPercent": 8.5,
    "meetingRank": 34,
    "communityPercent": 9.1,
    "communityRank": 24,
    "donatedPercent": 44.4,
    "donatedRank": 48,
    "votePercent": 50,
    "voteRank": 16,
    "registeredPercent": 74.9,
    "registeredRank": 3,
    "contactedPercent": 6.8,
    "contactedRank": 51,
    "productPercent": 4.7,
    "productRank": 50,
    "groupPercent": 13.3,
    "groupRank": 30,
    "organizationPercent": 6.9,
    "organizationRank": 30
  },
  {
    "state": "Maine",
    "year": 2010,
    "volunteerPercent": 30.8,
    "volunteerRank": 13,
    "volunteerHours": 35.8,
    "volunteerHoursRank": 6,
    "meetingPercent": 16.8,
    "meetingRank": 3,
    "communityPercent": 12.2,
    "communityRank": 11,
    "donatedPercent": 51.3,
    "donatedRank": 30,
    "votePercent": 59.4,
    "voteRank": 1,
    "registeredPercent": 76.6,
    "registeredRank": 1,
    "contactedPercent": 17.5,
    "contactedRank": 4,
    "productPercent": 15.9,
    "productRank": 7,
    "groupPercent": 15.2,
    "groupRank": 14,
    "organizationPercent": 10.1,
    "organizationRank": 10
  },
  {
    "state": "Maryland",
    "year": 2010,
    "volunteerPercent": 27,
    "volunteerRank": 21,
    "volunteerHours": 30.64,
    "volunteerHoursRank": 14,
    "meetingPercent": 10.9,
    "meetingRank": 19,
    "communityPercent": 9.5,
    "communityRank": 22,
    "donatedPercent": 56.7,
    "donatedRank": 14,
    "votePercent": 46.8,
    "voteRank": 26,
    "registeredPercent": 65.1,
    "registeredRank": 30,
    "contactedPercent": 9.4,
    "contactedRank": 33,
    "productPercent": 9.3,
    "productRank": 30,
    "groupPercent": 17.7,
    "groupRank": 4,
    "organizationPercent": 7,
    "organizationRank": 27
  },
  {
    "state": "Massachusetts",
    "year": 2010,
    "volunteerPercent": 26.3,
    "volunteerRank": 27,
    "volunteerHours": 25.45,
    "volunteerHoursRank": 30,
    "meetingPercent": 10.9,
    "meetingRank": 19,
    "communityPercent": 7.8,
    "communityRank": 31,
    "donatedPercent": 53.2,
    "donatedRank": 23,
    "votePercent": 52.2,
    "voteRank": 11,
    "registeredPercent": 68.8,
    "registeredRank": 14,
    "contactedPercent": 13,
    "contactedRank": 17,
    "productPercent": 11.2,
    "productRank": 18,
    "groupPercent": 13.7,
    "groupRank": 24,
    "organizationPercent": 7,
    "organizationRank": 27
  },
  {
    "state": "Michigan",
    "year": 2010,
    "volunteerPercent": 26.6,
    "volunteerRank": 24,
    "volunteerHours": 20.29,
    "volunteerHoursRank": 46,
    "meetingPercent": 9.8,
    "meetingRank": 25,
    "communityPercent": 8.9,
    "communityRank": 25,
    "donatedPercent": 49.9,
    "donatedRank": 37,
    "votePercent": 47.3,
    "voteRank": 20,
    "registeredPercent": 71.4,
    "registeredRank": 8,
    "contactedPercent": 10.8,
    "contactedRank": 26,
    "productPercent": 12.7,
    "productRank": 13,
    "groupPercent": 12.3,
    "groupRank": 36,
    "organizationPercent": 6.9,
    "organizationRank": 30
  },
  {
    "state": "Minnesota",
    "year": 2010,
    "volunteerPercent": 37.4,
    "volunteerRank": 2,
    "volunteerHours": 36.72,
    "volunteerHoursRank": 5,
    "meetingPercent": 12.8,
    "meetingRank": 13,
    "communityPercent": 11.5,
    "communityRank": 12,
    "donatedPercent": 64,
    "donatedRank": 1,
    "votePercent": 54.9,
    "voteRank": 6,
    "registeredPercent": 72,
    "registeredRank": 7,
    "contactedPercent": 13.3,
    "contactedRank": 15,
    "productPercent": 13.6,
    "productRank": 10,
    "groupPercent": 14.9,
    "groupRank": 16,
    "organizationPercent": 9.4,
    "organizationRank": 13
  },
  {
    "state": "Mississippi",
    "year": 2010,
    "volunteerPercent": 24.1,
    "volunteerRank": 32,
    "volunteerHours": 31.37,
    "volunteerHoursRank": 12,
    "meetingPercent": 9.6,
    "meetingRank": 27,
    "communityPercent": 8,
    "communityRank": 30,
    "donatedPercent": 53.8,
    "donatedRank": 21,
    "votePercent": 47.1,
    "voteRank": 23,
    "registeredPercent": 73.4,
    "registeredRank": 5,
    "contactedPercent": 12.6,
    "contactedRank": 20,
    "productPercent": 5.4,
    "productRank": 49,
    "groupPercent": 14.3,
    "groupRank": 20,
    "organizationPercent": 7.1,
    "organizationRank": 26
  },
  {
    "state": "Missouri",
    "year": 2010,
    "volunteerPercent": 28.4,
    "volunteerRank": 18,
    "volunteerHours": 30.9,
    "volunteerHoursRank": 13,
    "meetingPercent": 9.6,
    "meetingRank": 27,
    "communityPercent": 10.2,
    "communityRank": 16,
    "donatedPercent": 50.2,
    "donatedRank": 34,
    "votePercent": 45.7,
    "voteRank": 29,
    "registeredPercent": 68.7,
    "registeredRank": 15,
    "contactedPercent": 9.1,
    "contactedRank": 35,
    "productPercent": 10.3,
    "productRank": 23,
    "groupPercent": 11.9,
    "groupRank": 41,
    "organizationPercent": 7,
    "organizationRank": 27
  },
  {
    "state": "Montana",
    "year": 2010,
    "volunteerPercent": 28.5,
    "volunteerRank": 17,
    "volunteerHours": 29.93,
    "volunteerHoursRank": 17,
    "meetingPercent": 21.2,
    "meetingRank": 1,
    "communityPercent": 14.1,
    "communityRank": 3,
    "donatedPercent": 57,
    "donatedRank": 12,
    "votePercent": 51.9,
    "voteRank": 12,
    "registeredPercent": 66,
    "registeredRank": 27,
    "contactedPercent": 19.1,
    "contactedRank": 1,
    "productPercent": 18.9,
    "productRank": 2,
    "groupPercent": 12.1,
    "groupRank": 39,
    "organizationPercent": 11.9,
    "organizationRank": 3
  },
  {
    "state": "Nebraska",
    "year": 2010,
    "volunteerPercent": 35.4,
    "volunteerRank": 4,
    "volunteerHours": 31.81,
    "volunteerHoursRank": 10,
    "meetingPercent": 11.8,
    "meetingRank": 16,
    "communityPercent": 9.9,
    "communityRank": 20,
    "donatedPercent": 58,
    "donatedRank": 7,
    "votePercent": 41.3,
    "voteRank": 43,
    "registeredPercent": 64.8,
    "registeredRank": 32,
    "contactedPercent": 13,
    "contactedRank": 17,
    "productPercent": 10.2,
    "productRank": 25,
    "groupPercent": 14.9,
    "groupRank": 16,
    "organizationPercent": 13,
    "organizationRank": 1
  },
  {
    "state": "Nevada",
    "year": 2010,
    "volunteerPercent": 19.2,
    "volunteerRank": 51,
    "volunteerHours": 37.3,
    "volunteerHoursRank": 4,
    "meetingPercent": 7.3,
    "meetingRank": 44,
    "communityPercent": 7,
    "communityRank": 40,
    "donatedPercent": 51,
    "donatedRank": 31,
    "votePercent": 42.4,
    "voteRank": 41,
    "registeredPercent": 57.8,
    "registeredRank": 49,
    "contactedPercent": 8.1,
    "contactedRank": 41,
    "productPercent": 12.6,
    "productRank": 14,
    "groupPercent": 8.5,
    "groupRank": 51,
    "organizationPercent": 3.5,
    "organizationRank": 50
  },
  {
    "state": "New Hampshire",
    "year": 2010,
    "volunteerPercent": 26.7,
    "volunteerRank": 22,
    "volunteerHours": 24.75,
    "volunteerHoursRank": 32,
    "meetingPercent": 15,
    "meetingRank": 4,
    "communityPercent": 10.2,
    "communityRank": 16,
    "donatedPercent": 57.9,
    "donatedRank": 8,
    "votePercent": 46.9,
    "voteRank": 25,
    "registeredPercent": 66.5,
    "registeredRank": 22,
    "contactedPercent": 13.5,
    "contactedRank": 9,
    "productPercent": 12.5,
    "productRank": 15,
    "groupPercent": 11.5,
    "groupRank": 44,
    "organizationPercent": 8.5,
    "organizationRank": 18
  },
  {
    "state": "New Jersey",
    "year": 2010,
    "volunteerPercent": 20.6,
    "volunteerRank": 46,
    "volunteerHours": 19.02,
    "volunteerHoursRank": 47,
    "meetingPercent": 7.9,
    "meetingRank": 40,
    "communityPercent": 5.3,
    "communityRank": 51,
    "donatedPercent": 55.8,
    "donatedRank": 18,
    "votePercent": 41.7,
    "voteRank": 42,
    "registeredPercent": 63.9,
    "registeredRank": 35,
    "contactedPercent": 8.7,
    "contactedRank": 38,
    "productPercent": 6.9,
    "productRank": 42,
    "groupPercent": 15.1,
    "groupRank": 15,
    "organizationPercent": 6.1,
    "organizationRank": 37
  },
  {
    "state": "New Mexico",
    "year": 2010,
    "volunteerPercent": 24.1,
    "volunteerRank": 32,
    "volunteerHours": 38.75,
    "volunteerHoursRank": 3,
    "meetingPercent": 10.8,
    "meetingRank": 23,
    "communityPercent": 8.6,
    "communityRank": 27,
    "donatedPercent": 47.6,
    "donatedRank": 41,
    "votePercent": 42.5,
    "voteRank": 40,
    "registeredPercent": 54.8,
    "registeredRank": 50,
    "contactedPercent": 14.1,
    "contactedRank": 8,
    "productPercent": 12.4,
    "productRank": 16,
    "groupPercent": 14.7,
    "groupRank": 18,
    "organizationPercent": 3.3,
    "organizationRank": 51
  },
  {
    "state": "New York",
    "year": 2010,
    "volunteerPercent": 20.5,
    "volunteerRank": 47,
    "volunteerHours": 21.71,
    "volunteerHoursRank": 44,
    "meetingPercent": 8.7,
    "meetingRank": 33,
    "communityPercent": 6.3,
    "communityRank": 47,
    "donatedPercent": 42.5,
    "donatedRank": 50,
    "votePercent": 43.6,
    "voteRank": 37,
    "registeredPercent": 63.8,
    "registeredRank": 36,
    "contactedPercent": 8.3,
    "contactedRank": 40,
    "productPercent": 9.2,
    "productRank": 31,
    "groupPercent": 10.9,
    "groupRank": 46,
    "organizationPercent": 5,
    "organizationRank": 46
  },
  {
    "state": "North Carolina",
    "year": 2010,
    "volunteerPercent": 22.4,
    "volunteerRank": 39,
    "volunteerHours": 21.64,
    "volunteerHoursRank": 45,
    "meetingPercent": 7.6,
    "meetingRank": 42,
    "communityPercent": 7.8,
    "communityRank": 31,
    "donatedPercent": 45.6,
    "donatedRank": 45,
    "votePercent": 45.4,
    "voteRank": 31,
    "registeredPercent": 67.2,
    "registeredRank": 18,
    "contactedPercent": 7.2,
    "contactedRank": 48,
    "productPercent": 7,
    "productRank": 40,
    "groupPercent": 13.6,
    "groupRank": 27,
    "organizationPercent": 5.3,
    "organizationRank": 42
  },
  {
    "state": "North Dakota",
    "year": 2010,
    "volunteerPercent": 30.9,
    "volunteerRank": 11,
    "volunteerHours": 23.69,
    "volunteerHoursRank": 37,
    "meetingPercent": 14.9,
    "meetingRank": 5,
    "communityPercent": 14,
    "communityRank": 4,
    "donatedPercent": 57.1,
    "donatedRank": 11,
    "votePercent": 55.7,
    "voteRank": 4,
    "registeredPercent": 75.6,
    "registeredRank": 2,
    "contactedPercent": 11.4,
    "contactedRank": 23,
    "productPercent": 6.8,
    "productRank": 43,
    "groupPercent": 10.4,
    "groupRank": 48,
    "organizationPercent": 10.4,
    "organizationRank": 9
  },
  {
    "state": "Ohio",
    "year": 2010,
    "volunteerPercent": 26.5,
    "volunteerRank": 25,
    "volunteerHours": 23.42,
    "volunteerHoursRank": 39,
    "meetingPercent": 8.5,
    "meetingRank": 34,
    "communityPercent": 7.7,
    "communityRank": 33,
    "donatedPercent": 48.5,
    "donatedRank": 38,
    "votePercent": 45.2,
    "voteRank": 33,
    "registeredPercent": 66.1,
    "registeredRank": 26,
    "contactedPercent": 11.4,
    "contactedRank": 23,
    "productPercent": 11.3,
    "productRank": 17,
    "groupPercent": 13.8,
    "groupRank": 23,
    "organizationPercent": 7.8,
    "organizationRank": 21
  },
  {
    "state": "Oklahoma",
    "year": 2010,
    "volunteerPercent": 26.5,
    "volunteerRank": 25,
    "volunteerHours": 24.81,
    "volunteerHoursRank": 31,
    "meetingPercent": 8.2,
    "meetingRank": 36,
    "communityPercent": 7.1,
    "communityRank": 39,
    "donatedPercent": 51,
    "donatedRank": 31,
    "votePercent": 40.4,
    "voteRank": 47,
    "registeredPercent": 61,
    "registeredRank": 44,
    "contactedPercent": 10.4,
    "contactedRank": 29,
    "productPercent": 7,
    "productRank": 40,
    "groupPercent": 13.2,
    "groupRank": 31,
    "organizationPercent": 6.3,
    "organizationRank": 34
  },
  {
    "state": "Oregon",
    "year": 2010,
    "volunteerPercent": 28.7,
    "volunteerRank": 16,
    "volunteerHours": 23.82,
    "volunteerHoursRank": 36,
    "meetingPercent": 10.5,
    "meetingRank": 24,
    "communityPercent": 10.7,
    "communityRank": 13,
    "donatedPercent": 55.9,
    "donatedRank": 17,
    "votePercent": 56.3,
    "voteRank": 3,
    "registeredPercent": 70.8,
    "registeredRank": 9,
    "contactedPercent": 16.9,
    "contactedRank": 6,
    "productPercent": 21.9,
    "productRank": 1,
    "groupPercent": 16,
    "groupRank": 9,
    "organizationPercent": 10.1,
    "organizationRank": 10
  },
  {
    "state": "Pennsylvania",
    "year": 2010,
    "volunteerPercent": 25.6,
    "volunteerRank": 29,
    "volunteerHours": 31.44,
    "volunteerHoursRank": 11,
    "meetingPercent": 9.3,
    "meetingRank": 30,
    "communityPercent": 8.2,
    "communityRank": 28,
    "donatedPercent": 51.6,
    "donatedRank": 26,
    "votePercent": 43.9,
    "voteRank": 35,
    "registeredPercent": 64.6,
    "registeredRank": 33,
    "contactedPercent": 9.4,
    "contactedRank": 33,
    "productPercent": 8.5,
    "productRank": 34,
    "groupPercent": 12.3,
    "groupRank": 36,
    "organizationPercent": 9.3,
    "organizationRank": 14
  },
  {
    "state": "Rhode Island",
    "year": 2010,
    "volunteerPercent": 23.8,
    "volunteerRank": 35,
    "volunteerHours": 24.3,
    "volunteerHoursRank": 34,
    "meetingPercent": 10.9,
    "meetingRank": 19,
    "communityPercent": 7.7,
    "communityRank": 33,
    "donatedPercent": 55.3,
    "donatedRank": 19,
    "votePercent": 46.7,
    "voteRank": 28,
    "registeredPercent": 68.4,
    "registeredRank": 16,
    "contactedPercent": 13,
    "contactedRank": 17,
    "productPercent": 13.8,
    "productRank": 9,
    "groupPercent": 12,
    "groupRank": 40,
    "organizationPercent": 7.4,
    "organizationRank": 23
  },
  {
    "state": "South Carolina",
    "year": 2010,
    "volunteerPercent": 23.7,
    "volunteerRank": 36,
    "volunteerHours": 23.47,
    "volunteerHoursRank": 38,
    "meetingPercent": 9,
    "meetingRank": 32,
    "communityPercent": 9.3,
    "communityRank": 23,
    "donatedPercent": 51.4,
    "donatedRank": 28,
    "votePercent": 50.9,
    "voteRank": 14,
    "registeredPercent": 69,
    "registeredRank": 13,
    "contactedPercent": 10.5,
    "contactedRank": 28,
    "productPercent": 9.9,
    "productRank": 27,
    "groupPercent": 16.9,
    "groupRank": 7,
    "organizationPercent": 7.8,
    "organizationRank": 21
  },
  {
    "state": "South Dakota",
    "year": 2010,
    "volunteerPercent": 35.7,
    "volunteerRank": 3,
    "volunteerHours": 27.33,
    "volunteerHoursRank": 26,
    "meetingPercent": 14.7,
    "meetingRank": 6,
    "communityPercent": 16.3,
    "communityRank": 1,
    "donatedPercent": 56.7,
    "donatedRank": 14,
    "votePercent": 54.9,
    "voteRank": 6,
    "registeredPercent": 69.1,
    "registeredRank": 12,
    "contactedPercent": 13.5,
    "contactedRank": 9,
    "productPercent": 8.6,
    "productRank": 33,
    "groupPercent": 12.6,
    "groupRank": 33,
    "organizationPercent": 11.5,
    "organizationRank": 5
  },
  {
    "state": "Tennessee",
    "year": 2010,
    "volunteerPercent": 21.9,
    "volunteerRank": 42,
    "volunteerHours": 18.38,
    "volunteerHoursRank": 50,
    "meetingPercent": 7.1,
    "meetingRank": 46,
    "communityPercent": 6.2,
    "communityRank": 48,
    "donatedPercent": 53.2,
    "donatedRank": 23,
    "votePercent": 37.7,
    "voteRank": 50,
    "registeredPercent": 62.8,
    "registeredRank": 39,
    "contactedPercent": 7.7,
    "contactedRank": 45,
    "productPercent": 8.8,
    "productRank": 32,
    "groupPercent": 13.7,
    "groupRank": 24,
    "organizationPercent": 6.1,
    "organizationRank": 37
  },
  {
    "state": "Texas",
    "year": 2010,
    "volunteerPercent": 22.6,
    "volunteerRank": 38,
    "volunteerHours": 27.9,
    "volunteerHoursRank": 24,
    "meetingPercent": 8.1,
    "meetingRank": 37,
    "communityPercent": 7,
    "communityRank": 40,
    "donatedPercent": 46.5,
    "donatedRank": 43,
    "votePercent": 36.4,
    "voteRank": 51,
    "registeredPercent": 61.6,
    "registeredRank": 42,
    "contactedPercent": 7.1,
    "contactedRank": 49,
    "productPercent": 6.6,
    "productRank": 44,
    "groupPercent": 15.8,
    "groupRank": 11,
    "organizationPercent": 5.8,
    "organizationRank": 40
  },
  {
    "state": "Utah",
    "year": 2010,
    "volunteerPercent": 41.5,
    "volunteerRank": 1,
    "volunteerHours": 61.59,
    "volunteerHoursRank": 1,
    "meetingPercent": 13.4,
    "meetingRank": 12,
    "communityPercent": 13.5,
    "communityRank": 6,
    "donatedPercent": 63.2,
    "donatedRank": 2,
    "votePercent": 38.6,
    "voteRank": 49,
    "registeredPercent": 60.8,
    "registeredRank": 46,
    "contactedPercent": 12.5,
    "contactedRank": 21,
    "productPercent": 9.8,
    "productRank": 29,
    "groupPercent": 17.4,
    "groupRank": 5,
    "organizationPercent": 4.9,
    "organizationRank": 47
  },
  {
    "state": "Vermont",
    "year": 2010,
    "volunteerPercent": 33,
    "volunteerRank": 9,
    "volunteerHours": 34.15,
    "volunteerHoursRank": 8,
    "meetingPercent": 20.7,
    "meetingRank": 2,
    "communityPercent": 15.9,
    "communityRank": 2,
    "donatedPercent": 50.2,
    "donatedRank": 34,
    "votePercent": 55,
    "voteRank": 5,
    "registeredPercent": 74,
    "registeredRank": 4,
    "contactedPercent": 18.4,
    "contactedRank": 2,
    "productPercent": 17.5,
    "productRank": 3,
    "groupPercent": 14.5,
    "groupRank": 19,
    "organizationPercent": 11.4,
    "organizationRank": 6
  },
  {
    "state": "Virginia",
    "year": 2010,
    "volunteerPercent": 27.1,
    "volunteerRank": 20,
    "volunteerHours": 28.79,
    "volunteerHoursRank": 22,
    "meetingPercent": 9.1,
    "meetingRank": 31,
    "communityPercent": 10.2,
    "communityRank": 16,
    "donatedPercent": 53.3,
    "donatedRank": 22,
    "votePercent": 40.7,
    "voteRank": 45,
    "registeredPercent": 64,
    "registeredRank": 34,
    "contactedPercent": 7.3,
    "contactedRank": 47,
    "productPercent": 7.3,
    "productRank": 38,
    "groupPercent": 13.7,
    "groupRank": 24,
    "organizationPercent": 6.8,
    "organizationRank": 33
  },
  {
    "state": "Washington",
    "year": 2010,
    "volunteerPercent": 31.4,
    "volunteerRank": 10,
    "volunteerHours": 30.63,
    "volunteerHoursRank": 15,
    "meetingPercent": 14,
    "meetingRank": 9,
    "communityPercent": 12.8,
    "communityRank": 10,
    "donatedPercent": 60.8,
    "donatedRank": 4,
    "votePercent": 58.1,
    "voteRank": 2,
    "registeredPercent": 72.6,
    "registeredRank": 6,
    "contactedPercent": 13.5,
    "contactedRank": 9,
    "productPercent": 17.4,
    "productRank": 4,
    "groupPercent": 17.4,
    "groupRank": 5,
    "organizationPercent": 8.1,
    "organizationRank": 20
  },
  {
    "state": "West Virginia",
    "year": 2010,
    "volunteerPercent": 24.4,
    "volunteerRank": 31,
    "volunteerHours": 24.28,
    "volunteerHoursRank": 35,
    "meetingPercent": 6.8,
    "meetingRank": 50,
    "communityPercent": 7.4,
    "communityRank": 35,
    "donatedPercent": 43.7,
    "donatedRank": 49,
    "votePercent": 41,
    "voteRank": 44,
    "registeredPercent": 62.3,
    "registeredRank": 40,
    "contactedPercent": 8,
    "contactedRank": 43,
    "productPercent": 6.5,
    "productRank": 45,
    "groupPercent": 12.4,
    "groupRank": 35,
    "organizationPercent": 6.2,
    "organizationRank": 36
  },
  {
    "state": "Wisconsin",
    "year": 2010,
    "volunteerPercent": 35,
    "volunteerRank": 6,
    "volunteerHours": 30.47,
    "volunteerHoursRank": 16,
    "meetingPercent": 13.8,
    "meetingRank": 11,
    "communityPercent": 9.8,
    "communityRank": 21,
    "donatedPercent": 62,
    "donatedRank": 3,
    "votePercent": 54.3,
    "voteRank": 8,
    "registeredPercent": 70,
    "registeredRank": 11,
    "contactedPercent": 13.5,
    "contactedRank": 9,
    "productPercent": 13.3,
    "productRank": 12,
    "groupPercent": 13.5,
    "groupRank": 28,
    "organizationPercent": 9,
    "organizationRank": 16
  },
  {
    "state": "Wyoming",
    "year": 2010,
    "volunteerPercent": 30.8,
    "volunteerRank": 13,
    "volunteerHours": 27.42,
    "volunteerHoursRank": 25,
    "meetingPercent": 14.6,
    "meetingRank": 7,
    "communityPercent": 13.1,
    "communityRank": 9,
    "donatedPercent": 51.5,
    "donatedRank": 27,
    "votePercent": 47.2,
    "voteRank": 21,
    "registeredPercent": 59.6,
    "registeredRank": 48,
    "contactedPercent": 16.2,
    "contactedRank": 7,
    "productPercent": 10.6,
    "productRank": 22,
    "groupPercent": 11.5,
    "groupRank": 44,
    "organizationPercent": 11,
    "organizationRank": 8
  },
  {
    "state": "National Average",
    "year": 2010,
    "volunteerPercent": 24.9,
    "volunteerRank": "",
    "volunteerHours": 23.08,
    "volunteerHoursRank": "",
    "meetingPercent": 9.2,
    "meetingRank": "",
    "communityPercent": 8.1,
    "communityRank": "",
    "donatedPercent": 50.5,
    "donatedRank": "",
    "votePercent": 45.5,
    "voteRank": "",
    "registeredPercent": 65.1,
    "registeredRank": "",
    "contactedPercent": 9.7,
    "contactedRank": "",
    "productPercent": 9.8,
    "productRank": "",
    "groupPercent": 13.6,
    "groupRank": "",
    "organizationPercent": 6.6,
    "organizationRank": ""
  }
]
